yta_math_easings/__init__.py
yta_math_easings/abstract.py
yta_math_easings/animated/__init__.py
yta_math_easings/animated/abstract.py
yta_math_easings/animated/linear.py
yta_math_easings/animated/rush_from.py
yta_math_easings/animated/rush_into.py
yta_math_easings/animated/slow_into.py
yta_math_easings/animated/smooth.py
yta_math_easings/animated/smooth_step.py
yta_math_easings/animated/smoother_step.py
yta_math_easings/animated/smootherer_step.py
yta_math_easings/enums.py
yta_math_easings/linear.py
yta_math_easings/progress_mapping/__init__.py
yta_math_easings/progress_mapping/abstract.py
yta_math_easings/progress_mapping/linear.py
yta_math_easings/progress_mapping/pingpong.py
yta_math_easings/progress_mapping/reverse.py
yta_math_easings/rush_from.py
yta_math_easings/rush_into.py
yta_math_easings/slow_into.py
yta_math_easings/smooth.py
yta_math_easings/smooth_step.py
yta_math_easings/smoother_step.py
yta_math_easings/smootherer_step.py
yta_math_easings/utils.py
yta_math_easings-0.0.11.dist-info/licenses/LICENSE
yta_math_easings-0.0.11.dist-info/METADATA
yta_math_easings-0.0.11.dist-info/WHEEL
yta_math_easings-0.0.11.dist-info/RECORD
